{"Error":"","ErrorCode":0,"Guid":"","Id":0,"Success":true,"Value":[{"CI":43836733,"COI":231,"E":[{"C":1.78,"G":2,"P":1.5,"T":7},{"C":2.2,"G":2,"P":-1.5,"T":8},{"C":2.232,"G":17,"P":2.5,"T":10},{"C":1.76,"G":17,"P":2.5,"T":9},{"C":2.09,"G":15,"P":0.5,"T":12},{"C":1.74,"G":15,"P":0.5,"T":11},{"C":1.9,"G":62,"P":2,"T":14},{"C":1.9,"G":62,"P":2,"T":13},{"C":8.5,"G":1,"T":1},{"C":4.98,"G":1,"T":2},{"C":1.425,"G":1,"T":3},{"C":3.155,"G":8,"T":4},{"C":1.216,"G":8,"T":5},{"C":1.104,"G":8,"T":6},{"C":1.95,"G":19,"T":180},{"C":1.935,"G":19,"T":181}],"EC":1480,"GNS":true,"HLU":true,"HS":1,"HSI":true,"I":187831704,"L":"England. Premier League","LI":88637,"LR":"Чемпионат Англии. Премьер-лига","MIO":{"Loc":"St Mary's (Southampton)","TSt":"Round 33"},"MIS":[{"K":1,"V":"Round 33"},{"K":2,"V":"St Mary's (Southampton)"}],"MS":[0],"N":883,"O1":"Southampton","O1C":39,"O1I":2006,"O1IS":[2006],"O1R":"Саутгемптон","O2":"Liverpool","O2C":39,"O2I":1990,"O2IS":[1990],"O2R":"Ливерпуль","S":1554490800,"SGI":"5b223bc675cd2827cc242145","SI":1,"SN":"Football","SR":"Футбол","SS":2,"SSI":0,"SST":2,"T":1000,"TN":"Half","B":25204,"GSE":true,"SG":[{"CI":43836753,"E":[{"C":3.3,"G":15,"P":0.5,"T":11},{"C":1.33,"G":15,"P":0.5,"T":12},{"C":5.05,"G":19,"T":180},{"C":1.17,"G":19,"T":181},{"C":7.4,"G":1,"T":1},{"C":2.5,"G":1,"T":2},{"C":1.86,"G":1,"T":3},{"C":1.88,"G":8,"T":4},{"C":1.48,"G":8,"T":5},{"C":1.06,"G":8,"T":6},{"C":1.36,"G":2,"P":1,"T":7},{"C":3.15,"G":2,"P":-1,"T":8},{"C":2.2,"G":17,"P":1,"T":10},{"C":1.67,"G":17,"P":1,"T":9},{"C":1.58,"G":62,"P":1,"T":14},{"C":2.38,"G":62,"P":1,"T":13}],"EC":318,"I":187831705,"N":864,"P":1,"PN":"1  Half","SS":2,"T":1000},{"CI":43836759,"E":[{"C":2.76,"G":15,"P":0.5,"T":11},{"C":1.45,"G":15,"P":0.5,"T":12},{"C":3.78,"G":19,"T":180},{"C":1.27,"G":19,"T":181},{"C":7.1,"G":1,"T":1},{"C":2.96,"G":1,"T":2},{"C":1.685,"G":1,"T":3},{"C":2.11,"G":8,"T":4},{"C":1.36,"G":8,"T":5},{"C":1.064,"G":8,"T":6},{"C":1.56,"G":2,"P":1,"T":7},{"C":2.43,"G":2,"P":-1,"T":8},{"C":1.86,"G":17,"P":1.5,"T":10},{"C":1.94,"G":17,"P":1.5,"T":9},{"C":2.06,"G":62,"P":1,"T":14},{"C":1.76,"G":62,"P":1,"T":13}],"EC":277,"I":187831706,"N":1467,"P":2,"PN":"2  Half","SS":2,"T":1000},{"CI":44906997,"E":[{"C":1.1,"G":8,"T":6},{"C":1.05,"G":8,"T":5},{"C":3.9,"G":8,"T":4},{"C":5.8,"G":1,"T":1},{"C":1.25,"G":1,"T":3},{"C":9.7,"G":1,"T":2},{"C":1.85,"G":2,"P":3,"T":7},{"C":1.95,"G":2,"P":-3,"T":8},{"C":1.86,"G":15,"P":3.5,"T":12},{"C":1.88,"G":15,"P":3.5,"T":11},{"C":1.744,"G":62,"P":6.5,"T":14},{"C":2.01,"G":62,"P":6.5,"T":13},{"C":1.73,"G":17,"P":10.5,"T":10},{"C":2.03,"G":17,"P":10.5,"T":9}],"EC":225,"I":189689920,"N":59378,"SS":2,"T":1000,"TG":"Corners","TI":2},{"CI":44907027,"E":[{"C":1.19,"G":8,"T":6},{"C":1.13,"G":8,"T":5},{"C":2.6,"G":8,"T":4},{"C":1.9,"G":17,"P":4.5,"T":10},{"C":1.84,"G":17,"P":4.5,"T":9},{"C":4.34,"G":1,"T":1},{"C":1.47,"G":1,"T":3},{"C":5.3,"G":1,"T":2},{"C":1.88,"G":2,"P":1.5,"T":7},{"C":1.92,"G":2,"P":-1.5,"T":8},{"C":2.01,"G":15,"P":1.5,"T":12},{"C":1.8,"G":15,"P":1.5,"T":11},{"C":2.05,"G":62,"P":3,"T":14},{"C":1.77,"G":62,"P":3,"T":13}],"EC":125,"I":189689922,"N":59379,"P":1,"PN":"1  Half","SS":2,"T":1000,"TG":"Corners","TI":2},{"CI":44907047,"E":[{"C":1.18,"G":8,"T":6},{"C":1.11,"G":8,"T":5},{"C":2.8,"G":8,"T":4},{"C":1.69,"G":17,"P":5.5,"T":10},{"C":2.1,"G":17,"P":5.5,"T":9},{"C":4.44,"G":1,"T":1},{"C":1.42,"G":1,"T":3},{"C":5.9,"G":1,"T":2},{"C":1.96,"G":2,"P":1.5,"T":7},{"C":1.84,"G":2,"P":-1.5,"T":8},{"C":2.19,"G":15,"P":1.5,"T":12},{"C":1.68,"G":15,"P":1.5,"T":11},{"C":1.79,"G":62,"P":3.5,"T":14},{"C":2.02,"G":62,"P":3.5,"T":13}],"EC":108,"I":189689923,"N":59380,"P":2,"PN":"2  Half","SS":2,"T":1000,"TG":"Corners","TI":2},{"CI":44985477,"E":[{"C":1.72,"G":8,"T":6},{"C":1.26,"G":8,"T":5},{"C":1.36,"G":8,"T":4},{"C":2.064,"G":1,"T":1},{"C":2.984,"G":1,"T":3},{"C":3.9,"G":1,"T":2},{"C":1.72,"G":17,"P":3,"T":9},{"C":2.05,"G":17,"P":3,"T":10},{"C":1.54,"G":2,"T":7},{"C":2.37,"G":2,"T":8},{"C":1.616,"G":15,"P":1.5,"T":11},{"C":1.995,"G":62,"P":1.5,"T":13},{"C":2.23,"G":15,"P":1.5,"T":12},{"C":1.76,"G":62,"P":1.5,"T":14}],"EC":69,"I":189689914,"N":61899,"SS":2,"T":1000,"TG":"Yellow Cards","TI":8},{"CI":45030169,"E":[{"C":1.37,"G":8,"T":6},{"C":1.74,"G":8,"T":5},{"C":1.24,"G":8,"T":4},{"C":2.92,"G":1,"T":1},{"C":3.8,"G":1,"T":3},{"C":2.02,"G":1,"T":2},{"C":1.78,"G":15,"P":0.5,"T":12},{"C":2.04,"G":15,"P":0.5,"T":11},{"C":1.48,"G":62,"P":0.5,"T":14},{"C":2.645,"G":62,"P":0.5,"T":13},{"C":1.9,"G":17,"P":1,"T":9},{"C":1.85,"G":17,"P":1,"T":10},{"C":1.65,"G":2,"T":7},{"C":2.15,"G":2,"T":8}],"EC":28,"I":189689916,"N":61900,"P":1,"PN":"1  Half","SS":2,"T":1000,"TG":"Yellow Cards","TI":8},{"CI":45030159,"E":[{"C":1.6,"G":8,"T":6},{"C":1.35,"G":8,"T":5},{"C":1.34,"G":8,"T":4},{"C":2.26,"G":1,"T":1},{"C":3.09,"G":1,"T":3},{"C":3.1,"G":1,"T":2},{"C":1.53,"G":15,"P":1.5,"T":12},{"C":2.5,"G":15,"P":1.5,"T":11},{"C":2.56,"G":62,"P":0.5,"T":14},{"C":1.51,"G":62,"P":0.5,"T":13},{"C":1.82,"G":17,"P":2,"T":9},{"C":1.92,"G":17,"P":2,"T":10},{"C":1.65,"G":2,"T":7},{"C":2.15,"G":2,"T":8}],"EC":28,"I":189689918,"N":61901,"P":2,"PN":"2  Half","SS":2,"T":1000,"TG":"Yellow Cards","TI":8},{"CI":44965543,"E":[{"C":1.712,"G":17,"P":3,"T":9},{"C":2.13,"G":17,"P":3,"T":10},{"C":1.9,"G":2,"P":-0.5,"T":7},{"C":1.9,"G":2,"P":0.5,"T":8},{"C":1.664,"G":15,"P":1.5,"T":11},{"C":2.1,"G":15,"P":1.5,"T":12},{"C":2.5,"G":62,"P":1.5,"T":13},{"C":1.5,"G":62,"P":1.5,"T":14}],"EC":32,"I":189584161,"N":51425,"SS":2,"T":1000,"TG":"Cards","TI":10},{"CI":45044519,"E":[{"C":1.95,"G":2,"P":2.5,"T":7},{"C":1.8,"G":2,"P":-2.5,"T":8},{"C":1.864,"G":17,"P":9,"T":9},{"C":1.875,"G":17,"P":9,"T":10},{"C":6.3,"G":1,"T":1},{"C":10,"G":1,"T":2},{"C":1.21,"G":1,"T":3},{"C":4,"G":8,"T":4},{"C":1.02,"G":8,"T":5},{"C":1.08,"G":8,"T":6}],"EC":52,"I":189734953,"N":24242,"SS":2,"T":1000,"TG":"Shots On Target","TI":12},{"CI":45058017,"E":[{"C":1.75,"G":2,"P":1.5,"T":7},{"C":2,"G":2,"P":-1.5,"T":8},{"C":1.72,"G":17,"P":4,"T":9},{"C":2.05,"G":17,"P":4,"T":10},{"C":5.15,"G":1,"T":1},{"C":5.5,"G":1,"T":2},{"C":1.41,"G":1,"T":3},{"C":2.75,"G":8,"T":4},{"C":1.11,"G":8,"T":5},{"C":1.12,"G":8,"T":6},{"C":2.19,"G":15,"P":1.5,"T":11},{"C":1.63,"G":15,"P":1.5,"T":12},{"C":1.72,"G":62,"P":2.5,"T":13},{"C":2.05,"G":62,"P":2.5,"T":14}],"EC":22,"I":189734955,"N":24243,"P":1,"PN":"1  Half","SS":2,"T":1000,"TG":"Shots On Target","TI":12},{"CI":45058029,"E":[{"C":1.75,"G":2,"P":1.5,"T":7},{"C":2,"G":2,"P":-1.5,"T":8},{"C":1.75,"G":17,"P":4.5,"T":9},{"C":2,"G":17,"P":4.5,"T":10},{"C":4.7,"G":1,"T":1},{"C":6,"G":1,"T":2},{"C":1.43,"G":1,"T":3},{"C":2.65,"G":8,"T":4},{"C":1.09,"G":8,"T":5},{"C":1.15,"G":8,"T":6},{"C":1.8,"G":15,"P":1.5,"T":11},{"C":1.95,"G":15,"P":1.5,"T":12},{"C":1.57,"G":62,"P":2.5,"T":13},{"C":2.3,"G":62,"P":2.5,"T":14}],"EC":24,"I":189734957,"N":24244,"P":2,"PN":"2  Half","SS":2,"T":1000,"TG":"Shots On Target","TI":12},{"CI":45050997,"E":[{"C":1.55,"G":1,"T":1},{"C":5.25,"G":1,"T":2},{"C":4.1,"G":1,"T":3},{"C":1.18,"G":8,"T":4},{"C":1.12,"G":8,"T":5},{"C":2.35,"G":8,"T":6},{"C":1.87,"G":17,"P":4.5,"T":9},{"C":1.87,"G":17,"P":4.5,"T":10},{"C":1.85,"G":2,"P":-1,"T":7},{"C":1.89,"G":2,"P":1,"T":8},{"C":2.05,"G":15,"P":3,"T":11},{"C":2.145,"G":62,"P":2,"T":13},{"C":1.72,"G":15,"P":3,"T":12},{"C":1.65,"G":62,"P":2,"T":14}],"EC":48,"I":189721222,"N":31855,"SS":2,"T":1000,"TG":"Offsides","TI":13},{"CI":45057179,"E":[{"C":1.4,"G":2,"T":7},{"C":2.8,"G":2,"T":8},{"C":1.65,"G":17,"P":2,"T":9},{"C":2.15,"G":17,"P":2,"T":10},{"C":1.92,"G":1,"T":1},{"C":3.4,"G":1,"T":2},{"C":3.72,"G":1,"T":3},{"C":1.23,"G":8,"T":4},{"C":1.27,"G":8,"T":5},{"C":1.8,"G":8,"T":6},{"C":2.25,"G":15,"P":1.5,"T":11},{"C":1.6,"G":15,"P":1.5,"T":12},{"C":1.55,"G":62,"P":0.5,"T":13},{"C":2.35,"G":62,"P":0.5,"T":14}],"EC":22,"I":189733564,"N":31856,"P":1,"PN":"1  Half","SS":2,"T":1000,"TG":"Offsides","TI":13},{"CI":45057181,"E":[{"C":1.4,"G":2,"T":7},{"C":2.8,"G":2,"T":8},{"C":1.65,"G":17,"P":2,"T":9},{"C":2.15,"G":17,"P":2,"T":10},{"C":1.92,"G":1,"T":1},{"C":3.4,"G":1,"T":2},{"C":3.72,"G":1,"T":3},{"C":1.23,"G":8,"T":4},{"C":1.27,"G":8,"T":5},{"C":1.8,"G":8,"T":6},{"C":2.25,"G":15,"P":1.5,"T":11},{"C":1.6,"G":15,"P":1.5,"T":12},{"C":1.55,"G":62,"P":0.5,"T":13},{"C":2.35,"G":62,"P":0.5,"T":14}],"EC":24,"I":189733565,"N":31857,"P":2,"PN":"2  Half","SS":2,"T":1000,"TG":"Offsides","TI":13},{"CI":44854083,"E":[{"C":1.568,"G":1,"T":1},{"C":11,"G":1,"T":2},{"C":2.856,"G":1,"T":3},{"C":1.36,"G":8,"T":4},{"C":1.01,"G":8,"T":5},{"C":2.3,"G":8,"T":6},{"C":1.75,"G":17,"P":19.5,"T":9},{"C":2,"G":17,"P":19.5,"T":10},{"C":1.992,"G":2,"P":-2,"T":7},{"C":1.76,"G":2,"P":2,"T":8},{"C":1.81,"G":15,"P":10.5,"T":11},{"C":1.85,"G":62,"P":9,"T":13},{"C":1.93,"G":15,"P":10.5,"T":12},{"C":1.9,"G":62,"P":9,"T":14}],"EC":50,"I":189421895,"N":44629,"SS":2,"T":1000,"TG":"Fouls","TI":14},{"CI":45058023,"E":[{"C":2,"G":2,"P":-1,"T":7},{"C":1.75,"G":2,"P":1,"T":8},{"C":1.752,"G":17,"P":9,"T":9},{"C":1.995,"G":17,"P":9,"T":10},{"C":1.675,"G":1,"T":1},{"C":7,"G":1,"T":2},{"C":2.936,"G":1,"T":3},{"C":1.35,"G":8,"T":4},{"C":1.07,"G":8,"T":5},{"C":2.05,"G":8,"T":6},{"C":1.62,"G":15,"P":4.5,"T":11},{"C":2.2,"G":15,"P":4.5,"T":12},{"C":2.2,"G":62,"P":4.5,"T":13},{"C":1.62,"G":62,"P":4.5,"T":14}],"EC":22,"I":189734311,"N":44630,"P":1,"PN":"1  Half","SS":2,"T":1000,"TG":"Fouls","TI":14},{"CI":45058031,"E":[{"C":2.05,"G":2,"P":-1,"T":7},{"C":1.72,"G":2,"P":1,"T":8},{"C":1.92,"G":17,"P":10.5,"T":9},{"C":1.82,"G":17,"P":10.5,"T":10},{"C":1.72,"G":1,"T":1},{"C":7.5,"G":1,"T":2},{"C":2.832,"G":1,"T":3},{"C":1.39,"G":8,"T":4},{"C":1.07,"G":8,"T":5},{"C":2.1,"G":8,"T":6},{"C":1.9,"G":15,"P":5.5,"T":11},{"C":1.85,"G":15,"P":5.5,"T":12},{"C":1.7,"G":62,"P":4.5,"T":13},{"C":2.1,"G":62,"P":4.5,"T":14}],"EC":22,"I":189734313,"N":44631,"P":2,"PN":"2  Half","SS":2,"T":1000,"TG":"Fouls","TI":14},{"CI":44965537,"E":[],"EC":2,"I":189580650,"N":49229,"SS":2,"T":1000,"TG":"Posts and Crossbars","TI":27},{"CI":45098943,"E":[],"EC":2,"I":189789561,"N":49230,"P":1,"PN":"1  Half","SS":2,"T":1000,"TG":"Posts and Crossbars","TI":27},{"CI":45057015,"E":[{"C":1.87,"G":2,"P":24,"T":7},{"C":1.87,"G":2,"P":-24,"T":8}],"EC":6,"I":189733118,"N":28082,"SS":2,"T":1000,"TG":"Ball Possession","TI":29},{"CI":45098941,"E":[],"EC":5,"I":189790717,"N":50375,"SS":2,"T":1000,"TG":"Substitutions","TI":30},{"CI":45098939,"E":[{"C":4,"G":17,"P":0.5,"T":9},{"C":1.25,"G":17,"P":0.5,"T":10}],"EC":2,"I":189790718,"N":50376,"P":1,"PN":"1  Half","SS":2,"T":1000,"TG":"Substitutions","TI":30},{"CI":44906985,"E":[],"EC":15,"I":189494190,"N":59349,"SS":2,"T":1000,"TG":"Alternative Outcomes","TI":40},{"CI":44907013,"E":[],"EC":193,"I":189494210,"N":59417,"SS":2,"T":1000,"TG":"Accumulator Outcomes","TI":41},{"CI":44906991,"E":[],"EC":83,"I":189494199,"N":59366,"SS":2,"T":1000,"TG":"Cards. Stats","TI":42},{"CI":44907021,"E":[],"EC":3,"I":189494202,"N":59367,"P":1,"PN":"1  Half","SS":2,"T":1000,"TG":"Cards. Stats","TI":42},{"CI":44907037,"E":[],"EC":3,"I":189494208,"N":59368,"P":2,"PN":"2  Half","SS":2,"T":1000,"TG":"Cards. Stats","TI":42},{"CI":45095893,"E":[],"EC":35,"I":189787879,"N":53521,"SS":2,"T":1000,"TG":"Special bets","TI":45},{"CI":44857823,"E":[],"EC":2188,"I":189713194,"N":46559,"SS":2,"T":1000,"TG":"Players' stats","TI":52},{"CI":45058599,"E":[],"EC":10,"I":189736396,"N":46560,"P":1,"PN":"1  Half","SS":2,"T":1000,"TG":"Players' stats","TI":52},{"CI":45058601,"E":[],"EC":10,"I":189736397,"N":46561,"P":2,"PN":"2  Half","SS":2,"T":1000,"TG":"Players' stats","TI":52},{"CI":44854079,"E":[],"EC":4,"I":189421896,"N":44537,"SS":2,"T":1000,"TG":"Goal kicks","TI":53},{"CI":44854077,"E":[],"EC":4,"I":189421897,"N":44518,"SS":2,"T":1000,"TG":"Throw-ins","TI":55},{"CI":44864269,"E":[],"EC":14,"I":189436323,"N":44384,"SS":2,"T":1000,"TG":"1-minute events","TI":60},{"CI":44907005,"E":[],"EC":35,"I":189494186,"N":59395,"SS":2,"T":1000,"TG":"First To Happen","TI":67},{"CI":45098945,"E":[],"EC":6,"I":189789574,"N":59396,"P":1,"PN":"1  Half","SS":2,"T":1000,"TG":"First To Happen","TI":67},{"CI":45051005,"E":[{"C":2.095,"G":17,"P":23.5,"T":9},{"C":1.67,"G":17,"P":23.5,"T":10},{"C":1.45,"G":15,"P":7.5,"T":11},{"C":2.225,"G":15,"P":7.5,"T":12},{"C":1.91,"G":62,"P":15.5,"T":13},{"C":1.795,"G":62,"P":15.5,"T":14},{"C":1.864,"G":2,"P":6,"T":7},{"C":1.87,"G":2,"P":-6,"T":8},{"C":9.2,"G":1,"T":1},{"C":13,"G":1,"T":2},{"C":1.1,"G":1,"T":3},{"C":6,"G":8,"T":4},{"C":1.03,"G":8,"T":6}],"EC":25,"I":189721220,"N":32396,"SS":2,"T":1000,"TG":"Shots In The Direction Of The Goal","TI":95},{"CI":45058235,"E":[{"C":1.9,"G":2,"P":3,"T":7},{"C":1.85,"G":2,"P":-3,"T":8},{"C":1.992,"G":17,"P":11.5,"T":9},{"C":1.752,"G":17,"P":11.5,"T":10},{"C":6.3,"G":1,"T":1},{"C":11,"G":1,"T":2},{"C":1.2,"G":1,"T":3},{"C":4.14,"G":8,"T":4},{"C":1.01,"G":8,"T":5},{"C":1.08,"G":8,"T":6},{"C":2.3,"G":15,"P":4.5,"T":11},{"C":1.57,"G":15,"P":4.5,"T":12},{"C":2.15,"G":62,"P":7.5,"T":13},{"C":1.65,"G":62,"P":7.5,"T":14}],"EC":22,"I":189735874,"N":32397,"P":1,"PN":"1  Half","SS":2,"T":1000,"TG":"Shots In The Direction Of The Goal","TI":95},{"CI":45058237,"E":[{"C":1.85,"G":2,"P":3,"T":7},{"C":1.9,"G":2,"P":-3,"T":8},{"C":1.85,"G":17,"P":12.5,"T":9},{"C":1.9,"G":17,"P":12.5,"T":10},{"C":5.4,"G":1,"T":1},{"C":11,"G":1,"T":2},{"C":1.23,"G":1,"T":3},{"C":3.9,"G":8,"T":4},{"C":1.01,"G":8,"T":5},{"C":1.11,"G":8,"T":6},{"C":1.72,"G":15,"P":4.5,"T":11},{"C":2.05,"G":15,"P":4.5,"T":12},{"C":1.8,"G":62,"P":7.5,"T":13},{"C":1.95,"G":62,"P":7.5,"T":14}],"EC":22,"I":189735875,"N":32398,"P":2,"PN":"2  Half","SS":2,"T":1000,"TG":"Shots In The Direction Of The Goal","TI":95},{"CI":45050991,"E":[{"C":2.195,"G":17,"P":33.5,"T":9},{"C":1.6,"G":17,"P":33.5,"T":10},{"C":1.57,"G":15,"P":18.5,"T":11},{"C":2.25,"G":15,"P":18.5,"T":12},{"C":2.25,"G":62,"P":14.5,"T":13},{"C":1.57,"G":62,"P":14.5,"T":14}],"EC":6,"I":189721221,"N":31774,"SS":2,"T":1000,"TG":"Tackles","TI":102}]},{"CI":43836787,"COI":231,"E":[{"C":1.53,"G":2,"T":7},{"C":2.75,"G":2,"T":8},{"C":2.05,"G":17,"P":2.5,"T":10},{"C":1.87,"G":17,"P":2.5,"T":9},{"C":2.1,"G":1,"T":1},{"C":3.64,"G":1,"T":2},{"C":3.72,"G":1,"T":3},{"C":1.33,"G":8,"T":4},{"C":1.34,"G":8,"T":5},{"C":1.85,"G":8,"T":6},{"C":1.91,"G":15,"P":1.5,"T":11},{"C":1.8,"G":15,"P":1.5,"T":12},{"C":1.88,"G":62,"P":1,"T":14},{"C":1.92,"G":62,"P":1,"T":13},{"C":1.7,"G":19,"T":180},{"C":2.264,"G":19,"T":181}],"EC":1417,"GNS":true,"HLU":true,"HS":1,"HSI":true,"I":187831707,"L":"England. Premier League","LI":88637,"LR":"Чемпионат Англии. Премьер-лига","MIO":{"Loc":"Vitality (Bournemouth)","TSt":"Round 33"},"MIS":[{"K":1,"V":"Round 33"},{"K":2,"V":"Vitality (Bournemouth)"}],"MS":[0],"N":807,"O1":"Bournemouth","O1C":39,"O1I":18621,"O1IS":[18621],"O1R":"Борнмут","O2":"Burnley","O2C":39,"O2I":2036,"O2IS":[2036],"O2R":"Бернли","S":1554559200,"SGI":"5b223b7075cd2827cc242104","SI":1,"SN":"Football","SR":"Футбол","SS":2,"SSI":0,"SST":2,"T":1000,"TN":"Half","B":93604,"GSE":true,"SG":[]},{"CI":43836717,"COI":231,"E":[{"C":1.68,"G":2,"P":1,"T":7},{"C":2.375,"G":2,"P":-1,"T":8},{"C":1.88,"G":17,"P":2.5,"T":10},{"C":2.04,"G":17,"P":2.5,"T":9},{"C":5.2,"G":1,"T":1},{"C":3.86,"G":1,"T":2},{"C":1.76,"G":1,"T":3},{"C":2.23,"G":8,"T":4},{"C":1.31,"G":8,"T":5},{"C":1.2,"G":8,"T":6},{"C":2.25,"G":15,"P":0.5,"T":12},{"C":1.57,"G":15,"P":0.5,"T":11},{"C":1.83,"G":62,"P":1.5,"T":13},{"C":1.83,"G":62,"P":1.5,"T":14},{"C":1.95,"G":19,"T":180},{"C":1.935,"G":19,"T":181}],"EC":1417,"GNS":true,"HLU":true,"HS":1,"HSI":true,"I":187831692,"L":"England. Premier League","LI":88637,"LR":"Чемпионат Англии. Премьер-лига","MIO":{"Loc":"Kirklees (Huddersfield)","TSt":"Round 33"},"MIS":[{"K":1,"V":"Round 33"},{"K":2,"V":"Kirklees (Huddersfield)"}],"MS":[0],"N":873,"O1":"Huddersfield Town","O1C":39,"O1I":2048,"O1IS":[2048],"O1R":"Хаддерсфилд Таун","O2":"Leicester City","O2C":39,"O2I":2024,"O2IS":[2024],"O2R":"Лестер Сити","S":1554559200,"SGI":"5b223d2075cd2827cc24228f","SI":1,"SN":"Football","SR":"Футбол","SS":2,"SSI":0,"SST":2,"T":1000,"TN":"Half","B":93604,"GSE":true,"SG":[]},{"CI":43836731,"COI":231,"E":[{"C":1.78,"G":2,"T":7},{"C":2.2,"G":2,"T":8},{"C":1.71,"G":17,"P":2.5,"T":10},{"C":2.28,"G":17,"P":2.5,"T":9},{"C":2.55,"G":1,"T":1},{"C":3.26,"G":1,"T":2},{"C":3.115,"G":1,"T":3},{"C":1.43,"G":8,"T":4},{"C":1.4,"G":8,"T":5},{"C":1.6,"G":8,"T":6},{"C":2.12,"G":15,"P":1,"T":12},{"C":1.72,"G":15,"P":1,"T":11},{"C":1.9,"G":62,"P":1,"T":14},{"C":1.9,"G":62,"P":1,"T":13},{"C":1.91,"G":19,"T":180},{"C":1.975,"G":19,"T":181}],"EC":1418,"GNS":true,"HLU":true,"HS":1,"HSI":true,"I":187831695,"L":"England. Premier League","LI":88637,"LR":"Чемпионат Англии. Премьер-лига","MIO":{"Loc":"St. James' Park (Newcastle upon Tyne)","TSt":"Round 33"},"MIS":[{"K":1,"V":"Round 33"},{"K":2,"V":"St. James' Park (Newcastle upon Tyne)"}],"MS":[0],"N":159,"O1":"Newcastle United","O1C":39,"O1I":2000,"O1IS":[2000],"O1R":"Ньюкасл Юнайтед","O2":"Crystal Palace","O2C":39,"O2I":2020,"O2IS":[2020],"O2R":"Кристал Пэлэс","S":1554559200,"SGI":"5b223b7075cd2827cc24211f","SI":1,"SN":"Football","SR":"Футбол","SS":2,"SSI":0,"SST":2,"T":1000,"TN":"Half","B":93604,"GSE":true,"SG":[]},{"CI":44843259,"COI":231,"DI":"3 Matches","E":[{"C":2.395,"G":1,"T":1},{"C":6.2,"G":1,"T":2},{"C":2.12,"G":1,"T":3},{"C":1.72,"G":8,"T":4},{"C":1.12,"G":8,"T":5},{"C":1.57,"G":8,"T":6},{"C":1.46,"G":15,"P":4.5,"T":12},{"C":2.75,"G":15,"P":4.5,"T":11},{"C":3.4,"G":62,"P":2.5,"T":14},{"C":1.32,"G":62,"P":2.5,"T":13},{"C":1.23,"G":2,"P":2.5,"T":7},{"C":4.2,"G":2,"P":-2.5,"T":8},{"C":2.55,"G":17,"P":6.5,"T":10},{"C":1.52,"G":17,"P":6.5,"T":9}],"EC":102,"GI":[{"Key":"statDay","Value":"Bournemouth;1554559200;18621#Burnley;1554559200;2036\/Newcastle United;1554559200;2000#Crystal Palace;1554559200;2020\/Huddersfield Town;1554559200;2048#Leicester City;1554559200;2024"}],"GNS":true,"HS":1,"I":189404613,"L":"England. Premier League","LI":88637,"LR":"Чемпионат Англии. Премьер-лига","MIO":{"TSt":"Round 33"},"MIS":[{"K":1,"V":"Round 33"}],"MS":[0],"N":22597,"O1":"Home (Goals)","O1C":225,"O1I":37429,"O1IS":[37429],"O1R":"Хозяева (голы)","O2":"Away (Goals)","O2C":225,"O2I":37431,"O2IS":[37431],"O2R":"Гости (голы)","S":1554559200,"SI":1,"SN":"Football","SR":"Футбол","SSI":0,"T":1000,"TN":"Half","B":93604,"SG":[]},{"CI":43836751,"COI":231,"E":[{"C":2.26,"G":2,"T":7},{"C":1.74,"G":2,"T":8},{"C":1.71,"G":17,"P":3,"T":10},{"C":2.16,"G":17,"P":3,"T":9},{"C":3.048,"G":1,"T":1},{"C":3.68,"G":1,"T":2},{"C":2.38,"G":1,"T":3},{"C":1.67,"G":8,"T":4},{"C":1.33,"G":8,"T":5},{"C":1.44,"G":8,"T":6},{"C":2.375,"G":15,"P":1.5,"T":11},{"C":1.53,"G":15,"P":1.5,"T":12},{"C":1.91,"G":62,"P":1.5,"T":13},{"C":1.8,"G":62,"P":1.5,"T":14},{"C":1.57,"G":19,"T":180},{"C":2.54,"G":19,"T":181}],"EC":1428,"GNS":true,"HLU":true,"HS":1,"HSI":true,"I":187832185,"L":"England. Premier League","LI":88637,"LR":"Чемпионат Англии. Премьер-лига","MIO":{"Loc":"Goodison Park (Liverpool)","TSt":"Round 33"},"MIS":[{"K":1,"V":"Round 33"},{"K":2,"V":"Goodison Park (Liverpool)"}],"MS":[0],"N":808,"O1":"Everton","O1C":39,"O1I":1992,"O1IS":[1992],"O1R":"Эвертон","O2":"Arsenal","O2C":225,"O2I":50679,"O2IS":[50679],"O2R":"Арсенал","S":1554642300,"SGI":"5b223c9075cd2827cc2421ed","SI":1,"SN":"Football","SR":"Футбол","SS":2,"SSI":0,"SST":2,"T":1000,"TN":"Half","B":176704,"GSE":true,"SG":[]},{"CI":43836775,"COI":231,"E":[{"C":1.95,"G":2,"P":-1.5,"T":7},{"C":1.98,"G":2,"P":1.5,"T":8},{"C":2,"G":17,"P":3,"T":10},{"C":1.83,"G":17,"P":3,"T":9},{"C":1.69,"G":15,"P":2.5,"T":12},{"C":2.17,"G":15,"P":2.5,"T":11},{"C":2.19,"G":62,"P":0.5,"T":14},{"C":1.68,"G":62,"P":0.5,"T":13},{"C":1.35,"G":1,"T":1},{"C":5.7,"G":1,"T":2},{"C":9.6,"G":1,"T":3},{"C":1.085,"G":8,"T":4},{"C":1.18,"G":8,"T":5},{"C":3.62,"G":8,"T":6},{"C":1.8,"G":19,"T":180},{"C":2.105,"G":19,"T":181}],"EC":1430,"GNS":true,"HLU":true,"HS":1,"HSI":true,"I":187832179,"L":"England. Premier League","LI":88637,"LR":"Чемпионат Англии. Премьер-лига","MIO":{"Loc":"Etihad (Manchester)","TSt":"Round 33"},"MIS":[{"K":1,"V":"Round 33"},{"K":2,"V":"Etihad (Manchester)"}],"MS":[0],"N":765,"O1":"Chelsea","O1C":39,"O1I":1988,"O1IS":[1988],"O1R":"Челси","O2":"West Ham United","O2C":39,"O2I":1980,"O2IS":[1980],"O2R":"Вест Хэм Юнайтед","S":1554750000,"SGI":"5b223c0375cd2827cc2421b7","SI":1,"SN":"Football","SR":"Футбол","SS":2,"SSI":0,"SST":2,"T":1000,"TN":"Half","B":284404,"GSE":true,"SG":[]},{"CI":44771487,"COI":231,"E":[{"C":1.96,"G":17,"P":2.5,"T":10},{"C":1.95,"G":17,"P":2.5,"T":9},{"C":1.83,"G":1,"T":1},{"C":3.88,"G":1,"T":2},{"C":4.62,"G":1,"T":3},{"C":1.24,"G":8,"T":4},{"C":1.31,"G":8,"T":5},{"C":2.13,"G":8,"T":6},{"C":2.51,"G":2,"P":-1,"T":7},{"C":1.616,"G":2,"P":1,"T":8},{"C":1.83,"G":15,"P":1.5,"T":11},{"C":1.83,"G":15,"P":1.5,"T":12},{"C":1.61,"G":62,"P":1,"T":14},{"C":2.32,"G":62,"P":1,"T":13},{"C":1.82,"G":19,"T":180},{"C":2.08,"G":19,"T":181}],"EC":1024,"GNS":true,"HS":1,"HSI":true,"I":189370749,"L":"England. Premier League","LI":88637,"LR":"Чемпионат Англии. Премьер-лига","MIO":{"Loc":"King Power (Leicester)","TSt":"Round 34"},"MIS":[{"K":1,"V":"Round 34"},{"K":2,"V":"King Power (Leicester)"}],"MS":[0],"N":547,"O1":"Leicester City","O1C":39,"O1I":2024,"O1IS":[2024],"O1R":"Лестер Сити","O2":"Newcastle United","O2C":39,"O2I":2000,"O2IS":[2000],"O2R":"Ньюкасл Юнайтед","S":1555095600,"SGI":"5b22374375cd2827cc241359","SI":1,"SN":"Football","SR":"Футбол","SS":2,"SSI":0,"SST":2,"T":1000,"TN":"Half","B":630004,"SG":[]},{"CI":44771479,"COI":231,"E":[{"C":1.79,"G":17,"P":3.5,"T":10},{"C":2.16,"G":17,"P":3.5,"T":9},{"C":1.175,"G":1,"T":1},{"C":8.6,"G":1,"T":2},{"C":19,"G":1,"T":3},{"C":1.025,"G":8,"T":4},{"C":1.104,"G":8,"T":5},{"C":6,"G":8,"T":6},{"C":1.79,"G":2,"P":-2,"T":7},{"C":2.18,"G":2,"P":2,"T":8},{"C":1.616,"G":62,"P":0.5,"T":14},{"C":2.2,"G":62,"P":0.5,"T":13},{"C":1.665,"G":15,"P":2.5,"T":11},{"C":2.1,"G":15,"P":2.5,"T":12},{"C":2.2,"G":19,"T":180},{"C":1.736,"G":19,"T":181}],"EC":1011,"GNS":true,"HS":1,"HSI":true,"I":189370746,"L":"England. Premier League","LI":88637,"LR":"Чемпионат Англии. Премьер-лига","MIO":{"Loc":"Tottenham Hotspur (London)","TSt":"Round 34"},"MIS":[{"K":1,"V":"Round 34"},{"K":2,"V":"Tottenham Hotspur (London)"}],"MS":[0],"N":468,"O1":"Tottenham Hotspur","O1C":39,"O1I":1984,"O1IS":[1984],"O1R":"Тоттенхэм Хотспур","O2":"Huddersfield Town","O2C":39,"O2I":2048,"O2IS":[2048],"O2R":"Хаддерсфилд Таун","S":1555155000,"SGI":"5b22394375cd2827cc241503","SI":1,"SN":"Football","SR":"Футбол","SS":2,"SSI":0,"SST":2,"T":1000,"TN":"Half","B":689404,"SG":[]},{"CI":44844129,"COI":231,"E":[{"C":1.87,"G":2,"P":-4,"T":7},{"C":1.87,"G":2,"P":4,"T":8},{"C":1.82,"G":17,"P":16.5,"T":9},{"C":1.92,"G":17,"P":16.5,"T":10},{"C":1.21,"G":1,"T":1},{"C":13,"G":1,"T":2},{"C":6.8,"G":1,"T":3},{"C":1.1,"G":8,"T":4},{"C":1.02,"G":8,"T":5},{"C":4.5,"G":8,"T":6},{"C":1.92,"G":15,"P":10.5,"T":11},{"C":1.82,"G":15,"P":10.5,"T":12},{"C":2,"G":62,"P":6.5,"T":13},{"C":1.75,"G":62,"P":6.5,"T":14}],"EC":85,"GI":[{"Key":"statDay","Value":"Tottenham Hotspur;1555155000;1984#Huddersfield Town;1555155000;2048\/Burnley;1555164000;2036#Cardiff City;1555164000;2014\/Brighton & Hove Albion;1555164000;2026#Bournemouth;1555164000;18621\/Southampton;1555164000;2006#Wolverhampton Wanderers;1555164000;2058\/Fulham;1555164000;1986#Everton;1555164000;1992\/Manchester United;1555173000;1996#West Ham United;1555173000;1980"}],"GNS":true,"HS":1,"I":189408068,"L":"England. Premier League","LI":88637,"LR":"Чемпионат Англии. Премьер-лига","MIO":{"TSt":"Round 34"},"MIS":[{"K":1,"V":"Round 34"}],"MS":[0],"N":30369,"O1":"Home (Goals)","O1C":225,"O1I":37429,"O1IS":[37429],"O1R":"Хозяева (голы)","O2":"Away (Goals)","O2C":225,"O2I":37431,"O2IS":[37431],"O2R":"Гости (голы)","S":1555155000,"SI":1,"SN":"Football","SR":"Футбол","SSI":0,"T":1000,"TN":"Half","B":689404,"SG":[]},{"CI":44771501,"COI":231,"E":[{"C":1.84,"G":17,"P":2.5,"T":10},{"C":2.09,"G":17,"P":2.5,"T":9},{"C":2.4,"G":1,"T":1},{"C":3.42,"G":1,"T":2},{"C":3.22,"G":1,"T":3},{"C":1.41,"G":8,"T":4},{"C":1.37,"G":8,"T":5},{"C":1.66,"G":8,"T":6},{"C":1.71,"G":2,"T":7},{"C":2.31,"G":2,"T":8},{"C":2.25,"G":15,"P":1.5,"T":11},{"C":1.57,"G":15,"P":1.5,"T":12},{"C":1.94,"G":62,"P":1,"T":14},{"C":1.86,"G":62,"P":1,"T":13},{"C":1.77,"G":19,"T":180},{"C":2.15,"G":19,"T":181}],"EC":1026,"GNS":true,"HS":1,"HSI":true,"I":189371011,"L":"England. Premier League","LI":88637,"LR":"Чемпионат Англии. Премьер-лига","MIO":{"Loc":"The American Express Community Stadium (Brighton)","TSt":"Round 34"},"MIS":[{"K":1,"V":"Round 34"},{"K":2,"V":"The American Express Community Stadium (Brighton)"}],"MS":[0],"N":8387,"O1":"Brighton & Hove Albion","O1C":39,"O1I":2026,"O1IS":[2026],"O1R":"Брайтон энд Хав Альбион","O2":"Bournemouth","O2C":39,"O2I":18621,"O2IS":[18621],"O2R":"Борнмут","S":1555164000,"SGI":"5b2236bb75cd2827cc2412d2","SI":1,"SN":"Football","SR":"Футбол","SS":2,"SSI":0,"SST":2,"T":1000,"TN":"Half","B":698404,"SG":[]},{"CI":44771507,"COI":231,"E":[{"C":1.77,"G":17,"P":2.5,"T":10},{"C":2.19,"G":17,"P":2.5,"T":9},{"C":2.04,"G":1,"T":1},{"C":3.5,"G":1,"T":2},{"C":4.12,"G":1,"T":3},{"C":1.28,"G":8,"T":4},{"C":1.36,"G":8,"T":5},{"C":1.9,"G":8,"T":6},{"C":2.69,"G":2,"P":-1,"T":7},{"C":1.39,"G":2,"P":1,"T":8},{"C":2.1,"G":15,"P":1.5,"T":11},{"C":1.665,"G":15,"P":1.5,"T":12},{"C":1.66,"G":62,"P":1,"T":14},{"C":2.22,"G":62,"P":1,"T":13},{"C":1.95,"G":19,"T":180},{"C":1.935,"G":19,"T":181}],"EC":1012,"GNS":true,"HS":1,"HSI":true,"I":189371014,"L":"England. Premier League","LI":88637,"LR":"Чемпионат Англии. Премьер-лига","MIO":{"Loc":"Turf Moor (Burnley)","TSt":"Round 34"},"MIS":[{"K":1,"V":"Round 34"},{"K":2,"V":"Turf Moor (Burnley)"}],"MS":[0],"N":402,"O1":"Burnley","O1C":39,"O1I":2036,"O1IS":[2036],"O1R":"Бернли","O2":"Cardiff City","O2C":39,"O2I":2014,"O2IS":[2014],"O2R":"Кардифф Сити","S":1555164000,"SGI":"5b2237e675cd2827cc2413f3","SI":1,"SN":"Football","SR":"Футбол","SS":2,"SSI":0,"SST":2,"T":1000,"TN":"Half","B":698404,"SG":[]},{"CI":44771505,"COI":231,"E":[{"C":1.53,"G":2,"P":1,"T":7},{"C":2.74,"G":2,"P":-1,"T":8},{"C":2.16,"G":17,"P":2.5,"T":10},{"C":1.79,"G":17,"P":2.5,"T":9},{"C":3.92,"G":1,"T":1},{"C":3.98,"G":1,"T":2},{"C":1.95,"G":1,"T":3},{"C":1.98,"G":8,"T":4},{"C":1.3,"G":8,"T":5},{"C":1.3,"G":8,"T":6},{"C":1.8,"G":62,"P":1.5,"T":13},{"C":1.91,"G":62,"P":1.5,"T":14},{"C":1.9,"G":15,"P":1,"T":12},{"C":1.9,"G":15,"P":1,"T":11},{"C":1.68,"G":19,"T":180},{"C":2.3,"G":19,"T":181}],"EC":1030,"GNS":true,"HS":1,"HSI":true,"I":189371139,"L":"England. Premier League","LI":88637,"LR":"Чемпионат Англии. Премьер-лига","MIO":{"Loc":"Craven Cottage (London)","TSt":"Round 34"},"MIS":[{"K":1,"V":"Round 34"},{"K":2,"V":"Craven Cottage (London)"}],"MS":[0],"N":6455,"O1":"Fulham","O1C":39,"O1I":1986,"O1IS":[1986],"O1R":"Фулхэм","O2":"Everton","O2C":39,"O2I":1992,"O2IS":[1992],"O2R":"Эвертон","S":1555164000,"SGI":"5b2236a775cd2827cc2412bd","SI":1,"SN":"Football","SR":"Футбол","SS":2,"SSI":0,"SST":2,"T":1000,"TN":"Half","B":698404,"SG":[]},{"CI":44771497,"COI":231,"E":[{"C":2.63,"G":1,"T":1},{"C":3.22,"G":1,"T":2},{"C":3.032,"G":1,"T":3},{"C":1.44,"G":8,"T":4},{"C":1.41,"G":8,"T":5},{"C":1.57,"G":8,"T":6},{"C":1.83,"G":2,"T":7},{"C":2.12,"G":2,"T":8},{"C":1.71,"G":17,"P":2,"T":9},{"C":2.1,"G":17,"P":2,"T":10},{"C":2.03,"G":15,"P":1,"T":12},{"C":1.79,"G":15,"P":1,"T":11},{"C":1.88,"G":62,"P":1,"T":14},{"C":1.92,"G":62,"P":1,"T":13},{"C":1.95,"G":19,"T":180},{"C":1.935,"G":19,"T":181}],"EC":1021,"GNS":true,"HS":1,"HSI":true,"I":189371136,"L":"England. Premier League","LI":88637,"LR":"Чемпионат Англии. Премьер-лига","MIO":{"Loc":"St Mary's (Southampton)","TSt":"Round 34"},"MIS":[{"K":1,"V":"Round 34"},{"K":2,"V":"St Mary's (Southampton)"}],"MS":[0],"N":6457,"O1":"Southampton","O1C":39,"O1I":2006,"O1IS":[2006],"O1R":"Саутгемптон","O2":"Wolverhampton Wanderers","O2C":39,"O2I":2058,"O2IS":[2058],"O2R":"Вулверхэмптон","S":1555164000,"SGI":"5b2234f775cd2827cc24112f","SI":1,"SN":"Football","SR":"Футбол","SS":2,"SSI":0,"SST":2,"T":1000,"TN":"Half","B":698404,"SG":[]},{"CI":44771499,"COI":231,"E":[{"C":1.455,"G":1,"T":1},{"C":4.94,"G":1,"T":2},{"C":7.7,"G":1,"T":3},{"C":1.12,"G":8,"T":4},{"C":1.22,"G":8,"T":5},{"C":3.04,"G":8,"T":6},{"C":2.2,"G":2,"P":-1.5,"T":7},{"C":1.78,"G":2,"P":1.5,"T":8},{"C":1.85,"G":17,"P":3,"T":9},{"C":1.96,"G":17,"P":3,"T":10},{"C":2.32,"G":15,"P":2.5,"T":11},{"C":1.59,"G":15,"P":2.5,"T":12},{"C":1.58,"G":62,"P":0.5,"T":13},{"C":2.35,"G":62,"P":0.5,"T":14},{"C":1.75,"G":19,"T":180},{"C":2.18,"G":19,"T":181}],"EC":813,"GNS":true,"HS":1,"HSI":true,"I":189371133,"L":"England. Premier League","LI":88637,"LR":"Чемпионат Англии. Премьер-лига","MIO":{"Loc":"Old Trafford (Manchester)","TSt":"Round 34"},"MIS":[{"K":1,"V":"Round 34"},{"K":2,"V":"Old Trafford (Manchester)"}],"MS":[0],"N":6433,"O1":"Manchester United","O1C":39,"O1I":1996,"O1IS":[1996],"O1R":"Манчестер Юнайтед","O2":"West Ham United","O2C":39,"O2I":1980,"O2IS":[1980],"O2R":"Вест Хэм Юнайтед","S":1555173000,"SGI":"5b22357375cd2827cc2411ae","SI":1,"SN":"Football","SR":"Футбол","SS":2,"SSI":0,"SST":2,"T":1000,"TN":"Half","B":707404,"SG":[]},{"CI":44771495,"COI":231,"E":[{"C":11,"G":1,"T":1},{"C":6.15,"G":1,"T":2},{"C":1.31,"G":1,"T":3},{"C":3.94,"G":8,"T":4},{"C":1.16,"G":8,"T":5},{"C":1.07,"G":8,"T":6},{"C":2.07,"G":2,"P":1.5,"T":7},{"C":1.87,"G":2,"P":-1.5,"T":8},{"C":1.87,"G":17,"P":3,"T":9},{"C":1.94,"G":17,"P":3,"T":10},{"C":1.91,"G":15,"P":0.5,"T":12},{"C":1.8,"G":15,"P":0.5,"T":11},{"C":2.1,"G":62,"P":2.5,"T":13},{"C":1.665,"G":62,"P":2.5,"T":14},{"C":1.95,"G":19,"T":180},{"C":1.935,"G":19,"T":181}],"EC":1020,"GNS":true,"HS":1,"HSI":true,"I":189371142,"L":"England. Premier League","LI":88637,"LR":"Чемпионат Англии. Премьер-лига","MIO":{"Loc":"Selhurst Park (London)","TSt":"Round 34"},"MIS":[{"K":1,"V":"Round 34"},{"K":2,"V":"Selhurst Park (London)"}],"MS":[0],"N":6393,"O1":"Crystal Palace","O1C":39,"O1I":2020,"O1IS":[2020],"O1R":"Кристал Пэлэс","O2":"Manchester City","O2C":39,"O2I":1994,"O2IS":[1994],"O2R":"Манчестер Сити","S":1555247100,"SGI":"5b22385275cd2827cc24146a","SI":1,"SN":"Football","SR":"Футбол","SS":2,"SSI":0,"SST":2,"T":1000,"TN":"Half","B":781504,"SG":[]},{"CI":44843307,"COI":231,"DI":"2 Matches","E":[{"C":1.75,"G":2,"P":1,"T":7},{"C":2,"G":2,"P":-1,"T":8},{"C":1.87,"G":17,"P":6,"T":9},{"C":1.87,"G":17,"P":6,"T":10},{"C":3.165,"G":1,"T":1},{"C":6,"G":1,"T":2},{"C":1.77,"G":1,"T":3},{"C":2.1,"G":8,"T":4},{"C":1.13,"G":8,"T":5},{"C":1.35,"G":8,"T":6},{"C":1.85,"G":15,"P":2.5,"T":11},{"C":2,"G":62,"P":3.5,"T":13},{"C":1.9,"G":15,"P":2.5,"T":12},{"C":1.75,"G":62,"P":3.5,"T":14}],"EC":88,"GI":[{"Key":"statDay","Value":"Crystal Palace;1555247100;2020#Manchester City;1555247100;1994\/Liverpool;1555255800;1990#Chelsea;1555255800;1988"}],"GNS":true,"HS":1,"I":189404621,"L":"England. Premier League","LI":88637,"LR":"Чемпионат Англии. Премьер-лига","MIO":{"TSt":"Round 34"},"MIS":[{"K":1,"V":"Round 34"}],"MS":[0],"N":23492,"O1":"Home (Goals)","O1C":225,"O1I":37429,"O1IS":[37429],"O1R":"Хозяева (голы)","O2":"Away (Goals)","O2C":225,"O2I":37431,"O2IS":[37431],"O2R":"Гости (голы)","S":1555247100,"SI":1,"SN":"Football","SR":"Футбол","SSI":0,"T":1000,"TN":"Half","B":781504,"SG":[]},{"CI":44771489,"COI":231,"E":[{"C":1.7,"G":1,"T":1},{"C":4.2,"G":1,"T":2},{"C":5.2,"G":1,"T":3},{"C":1.2,"G":8,"T":4},{"C":1.28,"G":8,"T":5},{"C":2.34,"G":8,"T":6},{"C":2.17,"G":2,"P":-1,"T":7},{"C":1.8,"G":2,"P":1,"T":8},{"C":2.14,"G":17,"P":3,"T":9},{"C":1.69,"G":17,"P":3,"T":10},{"C":1.616,"G":15,"P":1.5,"T":11},{"C":2.2,"G":15,"P":1.5,"T":12},{"C":1.76,"G":62,"P":1,"T":14},{"C":2.06,"G":62,"P":1,"T":13},{"C":1.75,"G":19,"T":180},{"C":2.18,"G":19,"T":181}],"EC":1027,"GNS":true,"HS":1,"HSI":true,"I":189371334,"L":"England. Premier League","LI":88637,"LR":"Чемпионат Англии. Премьер-лига","MIO":{"Loc":"Anfield (Liverpool)","TSt":"Round 34"},"MIS":[{"K":1,"V":"Round 34"},{"K":2,"V":"Anfield (Liverpool)"}],"MS":[0],"N":5533,"O1":"Liverpool","O1C":39,"O1I":1990,"O1IS":[1990],"O1R":"Ливерпуль","O2":"Chelsea","O2C":39,"O2I":1988,"O2IS":[1988],"O2R":"Челси","S":1555255800,"SGI":"5b2238a775cd2827cc2414c4","SI":1,"SN":"Football","SR":"Футбол","SS":2,"SSI":0,"SST":2,"T":1000,"TN":"Half","B":790204,"SG":[]},{"CI":44770981,"COI":231,"E":[{"C":3.54,"G":1,"T":1},{"C":3.84,"G":1,"T":2},{"C":2.1,"G":1,"T":3},{"C":1.85,"G":8,"T":4},{"C":1.31,"G":8,"T":5},{"C":1.35,"G":8,"T":6},{"C":2.66,"G":2,"T":7},{"C":1.56,"G":2,"T":8},{"C":1.93,"G":17,"P":3,"T":9},{"C":1.88,"G":17,"P":3,"T":10},{"C":1.8,"G":62,"P":1.5,"T":13},{"C":1.91,"G":62,"P":1.5,"T":14},{"C":2.15,"G":15,"P":1,"T":12},{"C":1.7,"G":15,"P":1,"T":11},{"C":1.53,"G":19,"T":180},{"C":2.648,"G":19,"T":181}],"EC":1042,"GNS":true,"HS":1,"HSI":true,"I":189371337,"L":"England. Premier League","LI":88637,"LR":"Чемпионат Англии. Премьер-лига","MIO":{"Loc":"Vicarage Road (Watford)","TSt":"Round 34"},"MIS":[{"K":1,"V":"Round 34"},{"K":2,"V":"Vicarage Road (Watford)"}],"MS":[0],"N":22775,"O1":"Watford","O1C":39,"O1I":2018,"O1IS":[2018],"O1R":"Уотфорд","O2":"Arsenal","O2C":225,"O2I":50679,"O2IS":[50679],"O2R":"Арсенал","S":1555354800,"SGI":"5b2234f775cd2827cc24112b","SI":1,"SN":"Football","SR":"Футбол","SS":2,"SSI":0,"SST":2,"T":1000,"TN":"Half","B":889204,"SG":[]},{"CI":44117959,"COI":231,"E":[{"C":1.34,"G":1,"T":1},{"C":5.55,"G":1,"T":2},{"C":11,"G":1,"T":3},{"C":1.07,"G":8,"T":4},{"C":1.185,"G":8,"T":5},{"C":3.7,"G":8,"T":6},{"C":1.94,"G":2,"P":-1.5,"T":7},{"C":1.99,"G":2,"P":1.5,"T":8},{"C":2.07,"G":15,"P":2,"T":12},{"C":1.75,"G":15,"P":2,"T":11},{"C":1.76,"G":17,"P":3,"T":10},{"C":2.06,"G":17,"P":3,"T":9},{"C":1.84,"G":62,"P":0.5,"T":13},{"C":1.96,"G":62,"P":0.5,"T":14},{"C":1.97,"G":19,"T":180},{"C":1.83,"G":19,"T":181}],"EC":577,"GNS":true,"HS":1,"HSI":true,"I":189022037,"L":"England. Premier League","LI":88637,"LR":"Чемпионат Англии. Премьер-лига","MIO":{"Loc":"Tottenham Hotspur (London)","TSt":"Round 33"},"MIS":[{"K":1,"V":"Round 33"},{"K":2,"V":"Tottenham Hotspur (London)"}],"MS":[0],"N":2711,"O1":"Tottenham Hotspur","O1C":39,"O1I":1984,"O1IS":[1984],"O1R":"Тоттенхэм Хотспур","O2":"Brighton & Hove Albion","O2C":39,"O2I":2026,"O2IS":[2026],"O2R":"Брайтон энд Хав Альбион","S":1556045100,"SGI":"5b223c6d75cd2827cc2421d2","SI":1,"SN":"Football","SR":"Футбол","SS":2,"SSI":0,"SST":2,"T":1000,"TN":"Half","B":1579504,"SG":[]}]}